[{"arkumu":["http://w3id.org/arkumu/licenses/license-1","http://w3id.org/arkumu/licenses/license-2","http://w3id.org/arkumu/licenses/license-3"],"arkum":["http://w3id.org/arkumu/licenses/license-1","http://w3id.org/arkumu/licenses/license-2","http://w3id.org/arkumu/licenses/license-3"],"arku":["http://w3id.org/arkumu/licenses/license-1","http://w3id.org/arkumu/licenses/license-2","http://w3id.org/arkumu/licenses/license-3"],"ark":["http://w3id.org/arkumu/licenses/license-1","http://w3id.org/arkumu/licenses/license-2","http://w3id.org/arkumu/licenses/license-3"],"ar":["http://w3id.org/arkumu/licenses/license-1","http://w3id.org/arkumu/licenses/license-2","http://w3id.org/arkumu/licenses/license-3"],"a":["http://w3id.org/arkumu/licenses/license-1","http://w3id.org/arkumu/licenses/license-2","http://w3id.org/arkumu/licenses/license-3"],"rkumu":["http://w3id.org/arkumu/licenses/license-1","http://w3id.org/arkumu/licenses/license-2","http://w3id.org/arkumu/licenses/license-3"],"rkum":["http://w3id.org/arkumu/licenses/license-1","http://w3id.org/arkumu/licenses/license-2","http://w3id.org/arkumu/licenses/license-3"],"rku":["http://w3id.org/arkumu/licenses/license-1","http://w3id.org/arkumu/licenses/license-2","http://w3id.org/arkumu/licenses/license-3"],"rk":["http://w3id.org/arkumu/licenses/license-1","http://w3id.org/arkumu/licenses/license-2","http://w3id.org/arkumu/licenses/license-3"],"r":["http://w3id.org/arkumu/licenses/license-1","http://w3id.org/arkumu/licenses/license-2","http://w3id.org/arkumu/licenses/license-3"],"kumu":["http://w3id.org/arkumu/licenses/license-1","http://w3id.org/arkumu/licenses/license-2","http://w3id.org/arkumu/licenses/license-3"],"kum":["http://w3id.org/arkumu/licenses/license-1","http://w3id.org/arkumu/licenses/license-2","http://w3id.org/arkumu/licenses/license-3"],"ku":["http://w3id.org/arkumu/licenses/license-1","http://w3id.org/arkumu/licenses/license-2","http://w3id.org/arkumu/licenses/license-3"],"k":["http://w3id.org/arkumu/licenses/license-1","http://w3id.org/arkumu/licenses/license-2","http://w3id.org/arkumu/licenses/license-3"],"umu":["http://w3id.org/arkumu/licenses/license-1","http://w3id.org/arkumu/licenses/license-2","http://w3id.org/arkumu/licenses/license-3"],"um":["http://w3id.org/arkumu/licenses/license-1","http://w3id.org/arkumu/licenses/license-2","http://w3id.org/arkumu/licenses/license-3"],"u":["http://w3id.org/arkumu/licenses/license-1","http://w3id.org/arkumu/licenses/license-2","http://w3id.org/arkumu/licenses/license-3"],"mu":["http://w3id.org/arkumu/licenses/license-1","http://w3id.org/arkumu/licenses/license-2","http://w3id.org/arkumu/licenses/license-3"],"m":["http://w3id.org/arkumu/licenses/license-1","http://w3id.org/arkumu/licenses/license-10","http://w3id.org/arkumu/licenses/license-2","http://w3id.org/arkumu/licenses/license-3"],"pdm":["http://w3id.org/arkumu/licenses/license-10"],"pd":["http://w3id.org/arkumu/licenses/license-10"],"p":["http://w3id.org/arkumu/licenses/license-10"],"dm":["http://w3id.org/arkumu/licenses/license-10"],"d":["http://w3id.org/arkumu/licenses/license-10"],"n":["http://w3id.org/arkumu/licenses/license-11"],"i":["http://w3id.org/arkumu/licenses/license-11"],"in":["http://w3id.org/arkumu/licenses/license-11"],"c":["http://w3id.org/arkumu/licenses/license-4","http://w3id.org/arkumu/licenses/license-5","http://w3id.org/arkumu/licenses/license-6","http://w3id.org/arkumu/licenses/license-7","http://w3id.org/arkumu/licenses/license-8","http://w3id.org/arkumu/licenses/license-9"],"cc":["http://w3id.org/arkumu/licenses/license-4","http://w3id.org/arkumu/licenses/license-5","http://w3id.org/arkumu/licenses/license-6","http://w3id.org/arkumu/licenses/license-7","http://w3id.org/arkumu/licenses/license-8","http://w3id.org/arkumu/licenses/license-9"]},{"1":["http://w3id.org/arkumu/licenses/license-10"],"copyright":["http://w3id.org/arkumu/licenses/license-11"],"copyrigh":["http://w3id.org/arkumu/licenses/license-11"],"copyrig":["http://w3id.org/arkumu/licenses/license-11"],"copyri":["http://w3id.org/arkumu/licenses/license-11"],"copyr":["http://w3id.org/arkumu/licenses/license-11"],"copy":["http://w3id.org/arkumu/licenses/license-11"],"cop":["http://w3id.org/arkumu/licenses/license-11"],"co":["http://w3id.org/arkumu/licenses/license-11"],"c":["http://w3id.org/arkumu/licenses/license-11"],"b":["http://w3id.org/arkumu/licenses/license-4","http://w3id.org/arkumu/licenses/license-5","http://w3id.org/arkumu/licenses/license-6","http://w3id.org/arkumu/licenses/license-7","http://w3id.org/arkumu/licenses/license-8","http://w3id.org/arkumu/licenses/license-9"],"by":["http://w3id.org/arkumu/licenses/license-4","http://w3id.org/arkumu/licenses/license-5","http://w3id.org/arkumu/licenses/license-6","http://w3id.org/arkumu/licenses/license-7","http://w3id.org/arkumu/licenses/license-8","http://w3id.org/arkumu/licenses/license-9"]},{"0":["http://w3id.org/arkumu/licenses/license-10"],"1":["http://w3id.org/arkumu/licenses/license-1"],"4":["http://w3id.org/arkumu/licenses/license-4"],"public":["http://w3id.org/arkumu/licenses/license-10"],"publi":["http://w3id.org/arkumu/licenses/license-10"],"publ":["http://w3id.org/arkumu/licenses/license-10"],"pub":["http://w3id.org/arkumu/licenses/license-10"],"pu":["http://w3id.org/arkumu/licenses/license-10"],"opyright":["http://w3id.org/arkumu/licenses/license-11"],"opyrigh":["http://w3id.org/arkumu/licenses/license-11"],"opyrig":["http://w3id.org/arkumu/licenses/license-11"],"opyri":["http://w3id.org/arkumu/licenses/license-11"],"opyr":["http://w3id.org/arkumu/licenses/license-11"],"opy":["http://w3id.org/arkumu/licenses/license-11"],"op":["http://w3id.org/arkumu/licenses/license-11"],"o":["http://w3id.org/arkumu/licenses/license-11"],"pyright":["http://w3id.org/arkumu/licenses/license-11"],"pyrigh":["http://w3id.org/arkumu/licenses/license-11"],"pyrig":["http://w3id.org/arkumu/licenses/license-11"],"pyri":["http://w3id.org/arkumu/licenses/license-11"],"pyr":["http://w3id.org/arkumu/licenses/license-11"],"py":["http://w3id.org/arkumu/licenses/license-11"],"p":["http://w3id.org/arkumu/licenses/license-11"],"e":["http://w3id.org/arkumu/licenses/license-11"],"eu":["http://w3id.org/arkumu/licenses/license-11"],"orphaned":["http://w3id.org/arkumu/licenses/license-11"],"orphane":["http://w3id.org/arkumu/licenses/license-11"],"orphan":["http://w3id.org/arkumu/licenses/license-11"],"orpha":["http://w3id.org/arkumu/licenses/license-11"],"orph":["http://w3id.org/arkumu/licenses/license-11"],"orp":["http://w3id.org/arkumu/licenses/license-11"],"or":["http://w3id.org/arkumu/licenses/license-11"],"b":["http://w3id.org/arkumu/licenses/license-2","http://w3id.org/arkumu/licenses/license-3"],"y":["http://w3id.org/arkumu/licenses/license-4","http://w3id.org/arkumu/licenses/license-5","http://w3id.org/arkumu/licenses/license-6","http://w3id.org/arkumu/licenses/license-7","http://w3id.org/arkumu/licenses/license-8","http://w3id.org/arkumu/licenses/license-9"],"attribution":["http://w3id.org/arkumu/licenses/license-4","http://w3id.org/arkumu/licenses/license-5","http://w3id.org/arkumu/licenses/license-8","http://w3id.org/arkumu/licenses/license-9"],"attributio":["http://w3id.org/arkumu/licenses/license-4","http://w3id.org/arkumu/licenses/license-5","http://w3id.org/arkumu/licenses/license-8","http://w3id.org/arkumu/licenses/license-9"],"attributi":["http://w3id.org/arkumu/licenses/license-4","http://w3id.org/arkumu/licenses/license-5","http://w3id.org/arkumu/licenses/license-8","http://w3id.org/arkumu/licenses/license-9"],"attribut":["http://w3id.org/arkumu/licenses/license-4","http://w3id.org/arkumu/licenses/license-5","http://w3id.org/arkumu/licenses/license-8","http://w3id.org/arkumu/licenses/license-9"],"attribu":["http://w3id.org/arkumu/licenses/license-4","http://w3id.org/arkumu/licenses/license-5","http://w3id.org/arkumu/licenses/license-8","http://w3id.org/arkumu/licenses/license-9"],"attrib":["http://w3id.org/arkumu/licenses/license-4","http://w3id.org/arkumu/licenses/license-5","http://w3id.org/arkumu/licenses/license-8","http://w3id.org/arkumu/licenses/license-9"],"attri":["http://w3id.org/arkumu/licenses/license-4","http://w3id.org/arkumu/licenses/license-5","http://w3id.org/arkumu/licenses/license-8","http://w3id.org/arkumu/licenses/license-9"],"attr":["http://w3id.org/arkumu/licenses/license-4","http://w3id.org/arkumu/licenses/license-5","http://w3id.org/arkumu/licenses/license-8","http://w3id.org/arkumu/licenses/license-9"],"att":["http://w3id.org/arkumu/licenses/license-4","http://w3id.org/arkumu/licenses/license-5","http://w3id.org/arkumu/licenses/license-8","http://w3id.org/arkumu/licenses/license-9"],"at":["http://w3id.org/arkumu/licenses/license-4","http://w3id.org/arkumu/licenses/license-5","http://w3id.org/arkumu/licenses/license-8","http://w3id.org/arkumu/licenses/license-9"],"a":["http://w3id.org/arkumu/licenses/license-4","http://w3id.org/arkumu/licenses/license-5","http://w3id.org/arkumu/licenses/license-8"],"n":["http://w3id.org/arkumu/licenses/license-5","http://w3id.org/arkumu/licenses/license-6","http://w3id.org/arkumu/licenses/license-7","http://w3id.org/arkumu/licenses/license-8"],"nc":["http://w3id.org/arkumu/licenses/license-5","http://w3id.org/arkumu/licenses/license-6","http://w3id.org/arkumu/licenses/license-7"],"nd":["http://w3id.org/arkumu/licenses/license-8"],"s":["http://w3id.org/arkumu/licenses/license-9"],"sa":["http://w3id.org/arkumu/licenses/license-9"]},{"0":["http://w3id.org/arkumu/licenses/license-1","http://w3id.org/arkumu/licenses/license-4"],"1":["http://w3id.org/arkumu/licenses/license-2"],"4":["http://w3id.org/arkumu/licenses/license-5","http://w3id.org/arkumu/licenses/license-6","http://w3id.org/arkumu/licenses/license-7","http://w3id.org/arkumu/licenses/license-8","http://w3id.org/arkumu/licenses/license-9"],"ublic":["http://w3id.org/arkumu/licenses/license-10"],"ubli":["http://w3id.org/arkumu/licenses/license-10"],"ubl":["http://w3id.org/arkumu/licenses/license-10"],"ub":["http://w3id.org/arkumu/licenses/license-10"],"u":["http://w3id.org/arkumu/licenses/license-10","http://w3id.org/arkumu/licenses/license-11"],"blic":["http://w3id.org/arkumu/licenses/license-10"],"bli":["http://w3id.org/arkumu/licenses/license-10"],"bl":["http://w3id.org/arkumu/licenses/license-10"],"b":["http://w3id.org/arkumu/licenses/license-10"],"domain":["http://w3id.org/arkumu/licenses/license-10"],"domai":["http://w3id.org/arkumu/licenses/license-10"],"doma":["http://w3id.org/arkumu/licenses/license-10"],"dom":["http://w3id.org/arkumu/licenses/license-10"],"do":["http://w3id.org/arkumu/licenses/license-10"],"omain":["http://w3id.org/arkumu/licenses/license-10"],"omai":["http://w3id.org/arkumu/licenses/license-10"],"oma":["http://w3id.org/arkumu/licenses/license-10"],"om":["http://w3id.org/arkumu/licenses/license-10"],"o":["http://w3id.org/arkumu/licenses/license-10"],"yright":["http://w3id.org/arkumu/licenses/license-11"],"yrigh":["http://w3id.org/arkumu/licenses/license-11"],"yrig":["http://w3id.org/arkumu/licenses/license-11"],"yri":["http://w3id.org/arkumu/licenses/license-11"],"yr":["http://w3id.org/arkumu/licenses/license-11"],"y":["http://w3id.org/arkumu/licenses/license-11"],"right":["http://w3id.org/arkumu/licenses/license-11"],"righ":["http://w3id.org/arkumu/licenses/license-11"],"rig":["http://w3id.org/arkumu/licenses/license-11"],"ri":["http://w3id.org/arkumu/licenses/license-11","http://w3id.org/arkumu/licenses/license-4"],"r":["http://w3id.org/arkumu/licenses/license-11","http://w3id.org/arkumu/licenses/license-4"],"rphaned":["http://w3id.org/arkumu/licenses/license-11"],"rphane":["http://w3id.org/arkumu/licenses/license-11"],"rphan":["http://w3id.org/arkumu/licenses/license-11"],"rpha":["http://w3id.org/arkumu/licenses/license-11"],"rph":["http://w3id.org/arkumu/licenses/license-11"],"rp":["http://w3id.org/arkumu/licenses/license-11"],"c":["http://w3id.org/arkumu/licenses/license-3"],"ttribution":["http://w3id.org/arkumu/licenses/license-4","http://w3id.org/arkumu/licenses/license-5","http://w3id.org/arkumu/licenses/license-6","http://w3id.org/arkumu/licenses/license-7","http://w3id.org/arkumu/licenses/license-8","http://w3id.org/arkumu/licenses/license-9"],"ttributio":["http://w3id.org/arkumu/licenses/license-4","http://w3id.org/arkumu/licenses/license-5","http://w3id.org/arkumu/licenses/license-6","http://w3id.org/arkumu/licenses/license-7","http://w3id.org/arkumu/licenses/license-8","http://w3id.org/arkumu/licenses/license-9"],"ttributi":["http://w3id.org/arkumu/licenses/license-4","http://w3id.org/arkumu/licenses/license-5","http://w3id.org/arkumu/licenses/license-6","http://w3id.org/arkumu/licenses/license-7","http://w3id.org/arkumu/licenses/license-8","http://w3id.org/arkumu/licenses/license-9"],"ttribut":["http://w3id.org/arkumu/licenses/license-4","http://w3id.org/arkumu/licenses/license-5","http://w3id.org/arkumu/licenses/license-6","http://w3id.org/arkumu/licenses/license-7","http://w3id.org/arkumu/licenses/license-8","http://w3id.org/arkumu/licenses/license-9"],"ttribu":["http://w3id.org/arkumu/licenses/license-4","http://w3id.org/arkumu/licenses/license-5","http://w3id.org/arkumu/licenses/license-6","http://w3id.org/arkumu/licenses/license-7","http://w3id.org/arkumu/licenses/license-8","http://w3id.org/arkumu/licenses/license-9"],"ttrib":["http://w3id.org/arkumu/licenses/license-4","http://w3id.org/arkumu/licenses/license-5","http://w3id.org/arkumu/licenses/license-6","http://w3id.org/arkumu/licenses/license-7","http://w3id.org/arkumu/licenses/license-8","http://w3id.org/arkumu/licenses/license-9"],"ttri":["http://w3id.org/arkumu/licenses/license-4","http://w3id.org/arkumu/licenses/license-5","http://w3id.org/arkumu/licenses/license-6","http://w3id.org/arkumu/licenses/license-7","http://w3id.org/arkumu/licenses/license-8","http://w3id.org/arkumu/licenses/license-9"],"ttr":["http://w3id.org/arkumu/licenses/license-4","http://w3id.org/arkumu/licenses/license-5","http://w3id.org/arkumu/licenses/license-6","http://w3id.org/arkumu/licenses/license-7","http://w3id.org/arkumu/licenses/license-8","http://w3id.org/arkumu/licenses/license-9"],"tt":["http://w3id.org/arkumu/licenses/license-4","http://w3id.org/arkumu/licenses/license-5","http://w3id.org/arkumu/licenses/license-6","http://w3id.org/arkumu/licenses/license-7","http://w3id.org/arkumu/licenses/license-8","http://w3id.org/arkumu/licenses/license-9"],"t":["http://w3id.org/arkumu/licenses/license-4","http://w3id.org/arkumu/licenses/license-5","http://w3id.org/arkumu/licenses/license-6","http://w3id.org/arkumu/licenses/license-7","http://w3id.org/arkumu/licenses/license-8","http://w3id.org/arkumu/licenses/license-9"],"tribution":["http://w3id.org/arkumu/licenses/license-4","http://w3id.org/arkumu/licenses/license-5","http://w3id.org/arkumu/licenses/license-6","http://w3id.org/arkumu/licenses/license-7","http://w3id.org/arkumu/licenses/license-8","http://w3id.org/arkumu/licenses/license-9"],"tributio":["http://w3id.org/arkumu/licenses/license-4","http://w3id.org/arkumu/licenses/license-5","http://w3id.org/arkumu/licenses/license-6","http://w3id.org/arkumu/licenses/license-7","http://w3id.org/arkumu/licenses/license-8","http://w3id.org/arkumu/licenses/license-9"],"tributi":["http://w3id.org/arkumu/licenses/license-4","http://w3id.org/arkumu/licenses/license-5","http://w3id.org/arkumu/licenses/license-6","http://w3id.org/arkumu/licenses/license-7","http://w3id.org/arkumu/licenses/license-8","http://w3id.org/arkumu/licenses/license-9"],"tribut":["http://w3id.org/arkumu/licenses/license-4","http://w3id.org/arkumu/licenses/license-5","http://w3id.org/arkumu/licenses/license-6","http://w3id.org/arkumu/licenses/license-7","http://w3id.org/arkumu/licenses/license-8","http://w3id.org/arkumu/licenses/license-9"],"tribu":["http://w3id.org/arkumu/licenses/license-4","http://w3id.org/arkumu/licenses/license-5","http://w3id.org/arkumu/licenses/license-6","http://w3id.org/arkumu/licenses/license-7","http://w3id.org/arkumu/licenses/license-8","http://w3id.org/arkumu/licenses/license-9"],"trib":["http://w3id.org/arkumu/licenses/license-4","http://w3id.org/arkumu/licenses/license-5","http://w3id.org/arkumu/licenses/license-6","http://w3id.org/arkumu/licenses/license-7","http://w3id.org/arkumu/licenses/license-8","http://w3id.org/arkumu/licenses/license-9"],"tri":["http://w3id.org/arkumu/licenses/license-4","http://w3id.org/arkumu/licenses/license-5","http://w3id.org/arkumu/licenses/license-6","http://w3id.org/arkumu/licenses/license-7","http://w3id.org/arkumu/licenses/license-8","http://w3id.org/arkumu/licenses/license-9"],"tr":["http://w3id.org/arkumu/licenses/license-4","http://w3id.org/arkumu/licenses/license-5","http://w3id.org/arkumu/licenses/license-6","http://w3id.org/arkumu/licenses/license-7","http://w3id.org/arkumu/licenses/license-8","http://w3id.org/arkumu/licenses/license-9"],"ribution":["http://w3id.org/arkumu/licenses/license-4"],"ributio":["http://w3id.org/arkumu/licenses/license-4"],"ributi":["http://w3id.org/arkumu/licenses/license-4"],"ribut":["http://w3id.org/arkumu/licenses/license-4"],"ribu":["http://w3id.org/arkumu/licenses/license-4"],"rib":["http://w3id.org/arkumu/licenses/license-4"],"international":["http://w3id.org/arkumu/licenses/license-4"],"internationa":["http://w3id.org/arkumu/licenses/license-4"],"internation":["http://w3id.org/arkumu/licenses/license-4"],"internatio":["http://w3id.org/arkumu/licenses/license-4"],"internati":["http://w3id.org/arkumu/licenses/license-4"],"internat":["http://w3id.org/arkumu/licenses/license-4"],"interna":["http://w3id.org/arkumu/licenses/license-4"],"intern":["http://w3id.org/arkumu/licenses/license-4"],"inter":["http://w3id.org/arkumu/licenses/license-4"],"inte":["http://w3id.org/arkumu/licenses/license-4"],"int":["http://w3id.org/arkumu/licenses/license-4"],"in":["http://w3id.org/arkumu/licenses/license-4"],"noncommercial":["http://w3id.org/arkumu/licenses/license-5","http://w3id.org/arkumu/licenses/license-6","http://w3id.org/arkumu/licenses/license-7"],"noncommercia":["http://w3id.org/arkumu/licenses/license-5","http://w3id.org/arkumu/licenses/license-6","http://w3id.org/arkumu/licenses/license-7"],"noncommerci":["http://w3id.org/arkumu/licenses/license-5","http://w3id.org/arkumu/licenses/license-6","http://w3id.org/arkumu/licenses/license-7"],"noncommerc":["http://w3id.org/arkumu/licenses/license-5","http://w3id.org/arkumu/licenses/license-6","http://w3id.org/arkumu/licenses/license-7"],"noncommer":["http://w3id.org/arkumu/licenses/license-5","http://w3id.org/arkumu/licenses/license-6","http://w3id.org/arkumu/licenses/license-7"],"noncomme":["http://w3id.org/arkumu/licenses/license-5","http://w3id.org/arkumu/licenses/license-6","http://w3id.org/arkumu/licenses/license-7"],"noncomm":["http://w3id.org/arkumu/licenses/license-5","http://w3id.org/arkumu/licenses/license-6","http://w3id.org/arkumu/licenses/license-7"],"noncom":["http://w3id.org/arkumu/licenses/license-5","http://w3id.org/arkumu/licenses/license-6","http://w3id.org/arkumu/licenses/license-7"],"nonco":["http://w3id.org/arkumu/licenses/license-5","http://w3id.org/arkumu/licenses/license-6","http://w3id.org/arkumu/licenses/license-7"],"nonc":["http://w3id.org/arkumu/licenses/license-5","http://w3id.org/arkumu/licenses/license-6","http://w3id.org/arkumu/licenses/license-7"],"non":["http://w3id.org/arkumu/licenses/license-5","http://w3id.org/arkumu/licenses/license-6","http://w3id.org/arkumu/licenses/license-7"],"no":["http://w3id.org/arkumu/licenses/license-5","http://w3id.org/arkumu/licenses/license-6","http://w3id.org/arkumu/licenses/license-7","http://w3id.org/arkumu/licenses/license-8"],"oncommercial":["http://w3id.org/arkumu/licenses/license-5","http://w3id.org/arkumu/licenses/license-6","http://w3id.org/arkumu/licenses/license-7"],"oncommercia":["http://w3id.org/arkumu/licenses/license-5","http://w3id.org/arkumu/licenses/license-6","http://w3id.org/arkumu/licenses/license-7"],"oncommerci":["http://w3id.org/arkumu/licenses/license-5","http://w3id.org/arkumu/licenses/license-6","http://w3id.org/arkumu/licenses/license-7"],"oncommerc":["http://w3id.org/arkumu/licenses/license-5","http://w3id.org/arkumu/licenses/license-6","http://w3id.org/arkumu/licenses/license-7"],"oncommer":["http://w3id.org/arkumu/licenses/license-5","http://w3id.org/arkumu/licenses/license-6","http://w3id.org/arkumu/licenses/license-7"],"oncomme":["http://w3id.org/arkumu/licenses/license-5","http://w3id.org/arkumu/licenses/license-6","http://w3id.org/arkumu/licenses/license-7"],"oncomm":["http://w3id.org/arkumu/licenses/license-5","http://w3id.org/arkumu/licenses/license-6","http://w3id.org/arkumu/licenses/license-7"],"oncom":["http://w3id.org/arkumu/licenses/license-5","http://w3id.org/arkumu/licenses/license-6","http://w3id.org/arkumu/licenses/license-7"],"onco":["http://w3id.org/arkumu/licenses/license-5","http://w3id.org/arkumu/licenses/license-6","http://w3id.org/arkumu/licenses/license-7"],"onc":["http://w3id.org/arkumu/licenses/license-5","http://w3id.org/arkumu/licenses/license-6","http://w3id.org/arkumu/licenses/license-7"],"ncommercial":["http://w3id.org/arkumu/licenses/license-5","http://w3id.org/arkumu/licenses/license-6","http://w3id.org/arkumu/licenses/license-7"],"ncommercia":["http://w3id.org/arkumu/licenses/license-5","http://w3id.org/arkumu/licenses/license-6","http://w3id.org/arkumu/licenses/license-7"],"ncommerci":["http://w3id.org/arkumu/licenses/license-5","http://w3id.org/arkumu/licenses/license-6","http://w3id.org/arkumu/licenses/license-7"],"ncommerc":["http://w3id.org/arkumu/licenses/license-5","http://w3id.org/arkumu/licenses/license-6","http://w3id.org/arkumu/licenses/license-7"],"ncommer":["http://w3id.org/arkumu/licenses/license-5","http://w3id.org/arkumu/licenses/license-6","http://w3id.org/arkumu/licenses/license-7"],"ncomme":["http://w3id.org/arkumu/licenses/license-5","http://w3id.org/arkumu/licenses/license-6","http://w3id.org/arkumu/licenses/license-7"],"ncomm":["http://w3id.org/arkumu/licenses/license-5","http://w3id.org/arkumu/licenses/license-6","http://w3id.org/arkumu/licenses/license-7"],"ncom":["http://w3id.org/arkumu/licenses/license-5","http://w3id.org/arkumu/licenses/license-6","http://w3id.org/arkumu/licenses/license-7"],"nco":["http://w3id.org/arkumu/licenses/license-5","http://w3id.org/arkumu/licenses/license-6","http://w3id.org/arkumu/licenses/license-7"],"d":["http://w3id.org/arkumu/licenses/license-6","http://w3id.org/arkumu/licenses/license-8"],"nd":["http://w3id.org/arkumu/licenses/license-6"],"attribution":["http://w3id.org/arkumu/licenses/license-6","http://w3id.org/arkumu/licenses/license-7"],"attributio":["http://w3id.org/arkumu/licenses/license-6","http://w3id.org/arkumu/licenses/license-7"],"attributi":["http://w3id.org/arkumu/licenses/license-6","http://w3id.org/arkumu/licenses/license-7"],"attribut":["http://w3id.org/arkumu/licenses/license-6","http://w3id.org/arkumu/licenses/license-7"],"attribu":["http://w3id.org/arkumu/licenses/license-6","http://w3id.org/arkumu/licenses/license-7"],"attrib":["http://w3id.org/arkumu/licenses/license-6","http://w3id.org/arkumu/licenses/license-7"],"attri":["http://w3id.org/arkumu/licenses/license-6","http://w3id.org/arkumu/licenses/license-7"],"attr":["http://w3id.org/arkumu/licenses/license-6","http://w3id.org/arkumu/licenses/license-7"],"att":["http://w3id.org/arkumu/licenses/license-6","http://w3id.org/arkumu/licenses/license-7"],"at":["http://w3id.org/arkumu/licenses/license-6","http://w3id.org/arkumu/licenses/license-7"],"a":["http://w3id.org/arkumu/licenses/license-6","http://w3id.org/arkumu/licenses/license-7","http://w3id.org/arkumu/licenses/license-9"],"noderivatives":["http://w3id.org/arkumu/licenses/license-6","http://w3id.org/arkumu/licenses/license-8"],"noderivative":["http://w3id.org/arkumu/licenses/license-6","http://w3id.org/arkumu/licenses/license-8"],"noderivativ":["http://w3id.org/arkumu/licenses/license-6","http://w3id.org/arkumu/licenses/license-8"],"noderivati":["http://w3id.org/arkumu/licenses/license-6","http://w3id.org/arkumu/licenses/license-8"],"noderivat":["http://w3id.org/arkumu/licenses/license-6","http://w3id.org/arkumu/licenses/license-8"],"noderiva":["http://w3id.org/arkumu/licenses/license-6","http://w3id.org/arkumu/licenses/license-8"],"noderiv":["http://w3id.org/arkumu/licenses/license-6","http://w3id.org/arkumu/licenses/license-8"],"noderi":["http://w3id.org/arkumu/licenses/license-6","http://w3id.org/arkumu/licenses/license-8"],"noder":["http://w3id.org/arkumu/licenses/license-6","http://w3id.org/arkumu/licenses/license-8"],"node":["http://w3id.org/arkumu/licenses/license-6","http://w3id.org/arkumu/licenses/license-8"],"nod":["http://w3id.org/arkumu/licenses/license-6","http://w3id.org/arkumu/licenses/license-8"],"oderivatives":["http://w3id.org/arkumu/licenses/license-6","http://w3id.org/arkumu/licenses/license-8"],"oderivative":["http://w3id.org/arkumu/licenses/license-6","http://w3id.org/arkumu/licenses/license-8"],"oderivativ":["http://w3id.org/arkumu/licenses/license-6","http://w3id.org/arkumu/licenses/license-8"],"oderivati":["http://w3id.org/arkumu/licenses/license-6","http://w3id.org/arkumu/licenses/license-8"],"oderivat":["http://w3id.org/arkumu/licenses/license-6","http://w3id.org/arkumu/licenses/license-8"],"oderiva":["http://w3id.org/arkumu/licenses/license-6","http://w3id.org/arkumu/licenses/license-8"],"oderiv":["http://w3id.org/arkumu/licenses/license-6","http://w3id.org/arkumu/licenses/license-8"],"oderi":["http://w3id.org/arkumu/licenses/license-6","http://w3id.org/arkumu/licenses/license-8"],"oder":["http://w3id.org/arkumu/licenses/license-6","http://w3id.org/arkumu/licenses/license-8"],"ode":["http://w3id.org/arkumu/licenses/license-6","http://w3id.org/arkumu/licenses/license-8"],"od":["http://w3id.org/arkumu/licenses/license-6","http://w3id.org/arkumu/licenses/license-8"],"s":["http://w3id.org/arkumu/licenses/license-7"],"sa":["http://w3id.org/arkumu/licenses/license-7"],"sharealike":["http://w3id.org/arkumu/licenses/license-7","http://w3id.org/arkumu/licenses/license-9"],"sharealik":["http://w3id.org/arkumu/licenses/license-7","http://w3id.org/arkumu/licenses/license-9"],"shareali":["http://w3id.org/arkumu/licenses/license-7","http://w3id.org/arkumu/licenses/license-9"],"shareal":["http://w3id.org/arkumu/licenses/license-7","http://w3id.org/arkumu/licenses/license-9"],"sharea":["http://w3id.org/arkumu/licenses/license-7","http://w3id.org/arkumu/licenses/license-9"],"share":["http://w3id.org/arkumu/licenses/license-7","http://w3id.org/arkumu/licenses/license-9"],"shar":["http://w3id.org/arkumu/licenses/license-7","http://w3id.org/arkumu/licenses/license-9"],"sha":["http://w3id.org/arkumu/licenses/license-7","http://w3id.org/arkumu/licenses/license-9"],"sh":["http://w3id.org/arkumu/licenses/license-7","http://w3id.org/arkumu/licenses/license-9"],"derivatives":["http://w3id.org/arkumu/licenses/license-8"],"derivative":["http://w3id.org/arkumu/licenses/license-8"],"derivativ":["http://w3id.org/arkumu/licenses/license-8"],"derivati":["http://w3id.org/arkumu/licenses/license-8"],"derivat":["http://w3id.org/arkumu/licenses/license-8"],"deriva":["http://w3id.org/arkumu/licenses/license-8"],"deriv":["http://w3id.org/arkumu/licenses/license-8"],"deri":["http://w3id.org/arkumu/licenses/license-8"],"der":["http://w3id.org/arkumu/licenses/license-8"],"de":["http://w3id.org/arkumu/licenses/license-8"],"harealike":["http://w3id.org/arkumu/licenses/license-9"],"harealik":["http://w3id.org/arkumu/licenses/license-9"],"hareali":["http://w3id.org/arkumu/licenses/license-9"],"hareal":["http://w3id.org/arkumu/licenses/license-9"],"harea":["http://w3id.org/arkumu/licenses/license-9"],"hare":["http://w3id.org/arkumu/licenses/license-9"],"har":["http://w3id.org/arkumu/licenses/license-9"],"ha":["http://w3id.org/arkumu/licenses/license-9"],"h":["http://w3id.org/arkumu/licenses/license-9"]},{"0":["http://w3id.org/arkumu/licenses/license-2","http://w3id.org/arkumu/licenses/license-5","http://w3id.org/arkumu/licenses/license-6","http://w3id.org/arkumu/licenses/license-7","http://w3id.org/arkumu/licenses/license-8","http://w3id.org/arkumu/licenses/license-9"],"1":["http://w3id.org/arkumu/licenses/license-3"],"lic":["http://w3id.org/arkumu/licenses/license-10"],"li":["http://w3id.org/arkumu/licenses/license-10"],"l":["http://w3id.org/arkumu/licenses/license-10"],"ic":["http://w3id.org/arkumu/licenses/license-10"],"i":["http://w3id.org/arkumu/licenses/license-10","http://w3id.org/arkumu/licenses/license-4","http://w3id.org/arkumu/licenses/license-5","http://w3id.org/arkumu/licenses/license-6","http://w3id.org/arkumu/licenses/license-7","http://w3id.org/arkumu/licenses/license-8","http://w3id.org/arkumu/licenses/license-9"],"main":["http://w3id.org/arkumu/licenses/license-10"],"mai":["http://w3id.org/arkumu/licenses/license-10"],"ma":["http://w3id.org/arkumu/licenses/license-10"],"ain":["http://w3id.org/arkumu/licenses/license-10"],"ai":["http://w3id.org/arkumu/licenses/license-10"],"a":["http://w3id.org/arkumu/licenses/license-10"],"mark":["http://w3id.org/arkumu/licenses/license-10"],"mar":["http://w3id.org/arkumu/licenses/license-10"],"ark":["http://w3id.org/arkumu/licenses/license-10"],"ar":["http://w3id.org/arkumu/licenses/license-10","http://w3id.org/arkumu/licenses/license-7","http://w3id.org/arkumu/licenses/license-9"],"universal":["http://w3id.org/arkumu/licenses/license-10"],"universa":["http://w3id.org/arkumu/licenses/license-10"],"univers":["http://w3id.org/arkumu/licenses/license-10"],"univer":["http://w3id.org/arkumu/licenses/license-10"],"unive":["http://w3id.org/arkumu/licenses/license-10"],"univ":["http://w3id.org/arkumu/licenses/license-10"],"uni":["http://w3id.org/arkumu/licenses/license-10"],"un":["http://w3id.org/arkumu/licenses/license-10"],"ight":["http://w3id.org/arkumu/licenses/license-11"],"igh":["http://w3id.org/arkumu/licenses/license-11"],"ig":["http://w3id.org/arkumu/licenses/license-11"],"phaned":["http://w3id.org/arkumu/licenses/license-11"],"phane":["http://w3id.org/arkumu/licenses/license-11"],"phan":["http://w3id.org/arkumu/licenses/license-11"],"pha":["http://w3id.org/arkumu/licenses/license-11"],"ph":["http://w3id.org/arkumu/licenses/license-11"],"haned":["http://w3id.org/arkumu/licenses/license-11"],"hane":["http://w3id.org/arkumu/licenses/license-11"],"han":["http://w3id.org/arkumu/licenses/license-11"],"ha":["http://w3id.org/arkumu/licenses/license-11","http://w3id.org/arkumu/licenses/license-7"],"work":["http://w3id.org/arkumu/licenses/license-11"],"wor":["http://w3id.org/arkumu/licenses/license-11"],"wo":["http://w3id.org/arkumu/licenses/license-11"],"w":["http://w3id.org/arkumu/licenses/license-11"],"ibution":["http://w3id.org/arkumu/licenses/license-4","http://w3id.org/arkumu/licenses/license-5","http://w3id.org/arkumu/licenses/license-6","http://w3id.org/arkumu/licenses/license-7","http://w3id.org/arkumu/licenses/license-8","http://w3id.org/arkumu/licenses/license-9"],"ibutio":["http://w3id.org/arkumu/licenses/license-4","http://w3id.org/arkumu/licenses/license-5","http://w3id.org/arkumu/licenses/license-6","http://w3id.org/arkumu/licenses/license-7","http://w3id.org/arkumu/licenses/license-8","http://w3id.org/arkumu/licenses/license-9"],"ibuti":["http://w3id.org/arkumu/licenses/license-4","http://w3id.org/arkumu/licenses/license-5","http://w3id.org/arkumu/licenses/license-6","http://w3id.org/arkumu/licenses/license-7","http://w3id.org/arkumu/licenses/license-8","http://w3id.org/arkumu/licenses/license-9"],"ibut":["http://w3id.org/arkumu/licenses/license-4","http://w3id.org/arkumu/licenses/license-5","http://w3id.org/arkumu/licenses/license-6","http://w3id.org/arkumu/licenses/license-7","http://w3id.org/arkumu/licenses/license-8","http://w3id.org/arkumu/licenses/license-9"],"ibu":["http://w3id.org/arkumu/licenses/license-4","http://w3id.org/arkumu/licenses/license-5","http://w3id.org/arkumu/licenses/license-6","http://w3id.org/arkumu/licenses/license-7","http://w3id.org/arkumu/licenses/license-8","http://w3id.org/arkumu/licenses/license-9"],"ib":["http://w3id.org/arkumu/licenses/license-4","http://w3id.org/arkumu/licenses/license-5","http://w3id.org/arkumu/licenses/license-6","http://w3id.org/arkumu/licenses/license-7","http://w3id.org/arkumu/licenses/license-8","http://w3id.org/arkumu/licenses/license-9"],"bution":["http://w3id.org/arkumu/licenses/license-4","http://w3id.org/arkumu/licenses/license-5","http://w3id.org/arkumu/licenses/license-6","http://w3id.org/arkumu/licenses/license-7","http://w3id.org/arkumu/licenses/license-8","http://w3id.org/arkumu/licenses/license-9"],"butio":["http://w3id.org/arkumu/licenses/license-4","http://w3id.org/arkumu/licenses/license-5","http://w3id.org/arkumu/licenses/license-6","http://w3id.org/arkumu/licenses/license-7","http://w3id.org/arkumu/licenses/license-8","http://w3id.org/arkumu/licenses/license-9"],"buti":["http://w3id.org/arkumu/licenses/license-4","http://w3id.org/arkumu/licenses/license-5","http://w3id.org/arkumu/licenses/license-6","http://w3id.org/arkumu/licenses/license-7","http://w3id.org/arkumu/licenses/license-8","http://w3id.org/arkumu/licenses/license-9"],"but":["http://w3id.org/arkumu/licenses/license-4","http://w3id.org/arkumu/licenses/license-5","http://w3id.org/arkumu/licenses/license-6","http://w3id.org/arkumu/licenses/license-7","http://w3id.org/arkumu/licenses/license-8","http://w3id.org/arkumu/licenses/license-9"],"bu":["http://w3id.org/arkumu/licenses/license-4","http://w3id.org/arkumu/licenses/license-5","http://w3id.org/arkumu/licenses/license-6","http://w3id.org/arkumu/licenses/license-7","http://w3id.org/arkumu/licenses/license-8","http://w3id.org/arkumu/licenses/license-9"],"nternational":["http://w3id.org/arkumu/licenses/license-4","http://w3id.org/arkumu/licenses/license-5","http://w3id.org/arkumu/licenses/license-6","http://w3id.org/arkumu/licenses/license-7","http://w3id.org/arkumu/licenses/license-8","http://w3id.org/arkumu/licenses/license-9"],"nternationa":["http://w3id.org/arkumu/licenses/license-4","http://w3id.org/arkumu/licenses/license-5","http://w3id.org/arkumu/licenses/license-6","http://w3id.org/arkumu/licenses/license-7","http://w3id.org/arkumu/licenses/license-8","http://w3id.org/arkumu/licenses/license-9"],"nternation":["http://w3id.org/arkumu/licenses/license-4","http://w3id.org/arkumu/licenses/license-5","http://w3id.org/arkumu/licenses/license-6","http://w3id.org/arkumu/licenses/license-7","http://w3id.org/arkumu/licenses/license-8","http://w3id.org/arkumu/licenses/license-9"],"nternatio":["http://w3id.org/arkumu/licenses/license-4","http://w3id.org/arkumu/licenses/license-5","http://w3id.org/arkumu/licenses/license-6","http://w3id.org/arkumu/licenses/license-7","http://w3id.org/arkumu/licenses/license-8","http://w3id.org/arkumu/licenses/license-9"],"nternati":["http://w3id.org/arkumu/licenses/license-4","http://w3id.org/arkumu/licenses/license-5","http://w3id.org/arkumu/licenses/license-6","http://w3id.org/arkumu/licenses/license-7","http://w3id.org/arkumu/licenses/license-8","http://w3id.org/arkumu/licenses/license-9"],"nternat":["http://w3id.org/arkumu/licenses/license-4","http://w3id.org/arkumu/licenses/license-5","http://w3id.org/arkumu/licenses/license-6","http://w3id.org/arkumu/licenses/license-7","http://w3id.org/arkumu/licenses/license-8","http://w3id.org/arkumu/licenses/license-9"],"nterna":["http://w3id.org/arkumu/licenses/license-4","http://w3id.org/arkumu/licenses/license-5","http://w3id.org/arkumu/licenses/license-6","http://w3id.org/arkumu/licenses/license-7","http://w3id.org/arkumu/licenses/license-8","http://w3id.org/arkumu/licenses/license-9"],"ntern":["http://w3id.org/arkumu/licenses/license-4","http://w3id.org/arkumu/licenses/license-5","http://w3id.org/arkumu/licenses/license-6","http://w3id.org/arkumu/licenses/license-7","http://w3id.org/arkumu/licenses/license-8","http://w3id.org/arkumu/licenses/license-9"],"nter":["http://w3id.org/arkumu/licenses/license-4","http://w3id.org/arkumu/licenses/license-5","http://w3id.org/arkumu/licenses/license-6","http://w3id.org/arkumu/licenses/license-7","http://w3id.org/arkumu/licenses/license-8","http://w3id.org/arkumu/licenses/license-9"],"nte":["http://w3id.org/arkumu/licenses/license-4","http://w3id.org/arkumu/licenses/license-5","http://w3id.org/arkumu/licenses/license-6","http://w3id.org/arkumu/licenses/license-7","http://w3id.org/arkumu/licenses/license-8","http://w3id.org/arkumu/licenses/license-9"],"nt":["http://w3id.org/arkumu/licenses/license-4","http://w3id.org/arkumu/licenses/license-5","http://w3id.org/arkumu/licenses/license-6","http://w3id.org/arkumu/licenses/license-7","http://w3id.org/arkumu/licenses/license-8","http://w3id.org/arkumu/licenses/license-9"],"ternational":["http://w3id.org/arkumu/licenses/license-4","http://w3id.org/arkumu/licenses/license-5","http://w3id.org/arkumu/licenses/license-8","http://w3id.org/arkumu/licenses/license-9"],"ternationa":["http://w3id.org/arkumu/licenses/license-4","http://w3id.org/arkumu/licenses/license-5","http://w3id.org/arkumu/licenses/license-8","http://w3id.org/arkumu/licenses/license-9"],"ternation":["http://w3id.org/arkumu/licenses/license-4","http://w3id.org/arkumu/licenses/license-5","http://w3id.org/arkumu/licenses/license-8","http://w3id.org/arkumu/licenses/license-9"],"ternatio":["http://w3id.org/arkumu/licenses/license-4","http://w3id.org/arkumu/licenses/license-5","http://w3id.org/arkumu/licenses/license-8","http://w3id.org/arkumu/licenses/license-9"],"ternati":["http://w3id.org/arkumu/licenses/license-4","http://w3id.org/arkumu/licenses/license-5","http://w3id.org/arkumu/licenses/license-8","http://w3id.org/arkumu/licenses/license-9"],"ternat":["http://w3id.org/arkumu/licenses/license-4","http://w3id.org/arkumu/licenses/license-5","http://w3id.org/arkumu/licenses/license-8","http://w3id.org/arkumu/licenses/license-9"],"terna":["http://w3id.org/arkumu/licenses/license-4","http://w3id.org/arkumu/licenses/license-5","http://w3id.org/arkumu/licenses/license-8","http://w3id.org/arkumu/licenses/license-9"],"tern":["http://w3id.org/arkumu/licenses/license-4","http://w3id.org/arkumu/licenses/license-5","http://w3id.org/arkumu/licenses/license-8","http://w3id.org/arkumu/licenses/license-9"],"ter":["http://w3id.org/arkumu/licenses/license-4","http://w3id.org/arkumu/licenses/license-5","http://w3id.org/arkumu/licenses/license-8","http://w3id.org/arkumu/licenses/license-9"],"te":["http://w3id.org/arkumu/licenses/license-4","http://w3id.org/arkumu/licenses/license-5","http://w3id.org/arkumu/licenses/license-8","http://w3id.org/arkumu/licenses/license-9"],"ernational":["http://w3id.org/arkumu/licenses/license-4"],"ernationa":["http://w3id.org/arkumu/licenses/license-4"],"ernation":["http://w3id.org/arkumu/licenses/license-4"],"ernatio":["http://w3id.org/arkumu/licenses/license-4"],"ernati":["http://w3id.org/arkumu/licenses/license-4"],"ernat":["http://w3id.org/arkumu/licenses/license-4"],"erna":["http://w3id.org/arkumu/licenses/license-4"],"ern":["http://w3id.org/arkumu/licenses/license-4"],"er":["http://w3id.org/arkumu/licenses/license-4","http://w3id.org/arkumu/licenses/license-8"],"e":["http://w3id.org/arkumu/licenses/license-4","http://w3id.org/arkumu/licenses/license-8"],"ribution":["http://w3id.org/arkumu/licenses/license-5","http://w3id.org/arkumu/licenses/license-6","http://w3id.org/arkumu/licenses/license-7","http://w3id.org/arkumu/licenses/license-8","http://w3id.org/arkumu/licenses/license-9"],"ributio":["http://w3id.org/arkumu/licenses/license-5","http://w3id.org/arkumu/licenses/license-6","http://w3id.org/arkumu/licenses/license-7","http://w3id.org/arkumu/licenses/license-8","http://w3id.org/arkumu/licenses/license-9"],"ributi":["http://w3id.org/arkumu/licenses/license-5","http://w3id.org/arkumu/licenses/license-6","http://w3id.org/arkumu/licenses/license-7","http://w3id.org/arkumu/licenses/license-8","http://w3id.org/arkumu/licenses/license-9"],"ribut":["http://w3id.org/arkumu/licenses/license-5","http://w3id.org/arkumu/licenses/license-6","http://w3id.org/arkumu/licenses/license-7","http://w3id.org/arkumu/licenses/license-8","http://w3id.org/arkumu/licenses/license-9"],"ribu":["http://w3id.org/arkumu/licenses/license-5","http://w3id.org/arkumu/licenses/license-6","http://w3id.org/arkumu/licenses/license-7","http://w3id.org/arkumu/licenses/license-8","http://w3id.org/arkumu/licenses/license-9"],"rib":["http://w3id.org/arkumu/licenses/license-5","http://w3id.org/arkumu/licenses/license-6","http://w3id.org/arkumu/licenses/license-7","http://w3id.org/arkumu/licenses/license-8","http://w3id.org/arkumu/licenses/license-9"],"ri":["http://w3id.org/arkumu/licenses/license-5","http://w3id.org/arkumu/licenses/license-6","http://w3id.org/arkumu/licenses/license-7","http://w3id.org/arkumu/licenses/license-8","http://w3id.org/arkumu/licenses/license-9"],"r":["http://w3id.org/arkumu/licenses/license-5","http://w3id.org/arkumu/licenses/license-6","http://w3id.org/arkumu/licenses/license-7","http://w3id.org/arkumu/licenses/license-8","http://w3id.org/arkumu/licenses/license-9"],"commercial":["http://w3id.org/arkumu/licenses/license-5","http://w3id.org/arkumu/licenses/license-6","http://w3id.org/arkumu/licenses/license-7"],"commercia":["http://w3id.org/arkumu/licenses/license-5","http://w3id.org/arkumu/licenses/license-6","http://w3id.org/arkumu/licenses/license-7"],"commerci":["http://w3id.org/arkumu/licenses/license-5","http://w3id.org/arkumu/licenses/license-6","http://w3id.org/arkumu/licenses/license-7"],"commerc":["http://w3id.org/arkumu/licenses/license-5","http://w3id.org/arkumu/licenses/license-6","http://w3id.org/arkumu/licenses/license-7"],"commer":["http://w3id.org/arkumu/licenses/license-5","http://w3id.org/arkumu/licenses/license-6","http://w3id.org/arkumu/licenses/license-7"],"comme":["http://w3id.org/arkumu/licenses/license-5","http://w3id.org/arkumu/licenses/license-6","http://w3id.org/arkumu/licenses/license-7"],"comm":["http://w3id.org/arkumu/licenses/license-5","http://w3id.org/arkumu/licenses/license-6","http://w3id.org/arkumu/licenses/license-7"],"com":["http://w3id.org/arkumu/licenses/license-5","http://w3id.org/arkumu/licenses/license-6","http://w3id.org/arkumu/licenses/license-7"],"co":["http://w3id.org/arkumu/licenses/license-5","http://w3id.org/arkumu/licenses/license-6","http://w3id.org/arkumu/licenses/license-7"],"ommercial":["http://w3id.org/arkumu/licenses/license-5","http://w3id.org/arkumu/licenses/license-6","http://w3id.org/arkumu/licenses/license-7"],"ommercia":["http://w3id.org/arkumu/licenses/license-5","http://w3id.org/arkumu/licenses/license-6","http://w3id.org/arkumu/licenses/license-7"],"ommerci":["http://w3id.org/arkumu/licenses/license-5","http://w3id.org/arkumu/licenses/license-6","http://w3id.org/arkumu/licenses/license-7"],"ommerc":["http://w3id.org/arkumu/licenses/license-5","http://w3id.org/arkumu/licenses/license-6","http://w3id.org/arkumu/licenses/license-7"],"ommer":["http://w3id.org/arkumu/licenses/license-5","http://w3id.org/arkumu/licenses/license-6","http://w3id.org/arkumu/licenses/license-7"],"omme":["http://w3id.org/arkumu/licenses/license-5","http://w3id.org/arkumu/licenses/license-6","http://w3id.org/arkumu/licenses/license-7"],"omm":["http://w3id.org/arkumu/licenses/license-5","http://w3id.org/arkumu/licenses/license-6","http://w3id.org/arkumu/licenses/license-7"],"om":["http://w3id.org/arkumu/licenses/license-5","http://w3id.org/arkumu/licenses/license-6","http://w3id.org/arkumu/licenses/license-7"],"mmercial":["http://w3id.org/arkumu/licenses/license-5","http://w3id.org/arkumu/licenses/license-6","http://w3id.org/arkumu/licenses/license-7"],"mmercia":["http://w3id.org/arkumu/licenses/license-5","http://w3id.org/arkumu/licenses/license-6","http://w3id.org/arkumu/licenses/license-7"],"mmerci":["http://w3id.org/arkumu/licenses/license-5","http://w3id.org/arkumu/licenses/license-6","http://w3id.org/arkumu/licenses/license-7"],"mmerc":["http://w3id.org/arkumu/licenses/license-5","http://w3id.org/arkumu/licenses/license-6","http://w3id.org/arkumu/licenses/license-7"],"mmer":["http://w3id.org/arkumu/licenses/license-5","http://w3id.org/arkumu/licenses/license-6","http://w3id.org/arkumu/licenses/license-7"],"mme":["http://w3id.org/arkumu/licenses/license-5","http://w3id.org/arkumu/licenses/license-6","http://w3id.org/arkumu/licenses/license-7"],"mm":["http://w3id.org/arkumu/licenses/license-5","http://w3id.org/arkumu/licenses/license-6","http://w3id.org/arkumu/licenses/license-7"],"m":["http://w3id.org/arkumu/licenses/license-5","http://w3id.org/arkumu/licenses/license-6","http://w3id.org/arkumu/licenses/license-7"],"international":["http://w3id.org/arkumu/licenses/license-5","http://w3id.org/arkumu/licenses/license-6","http://w3id.org/arkumu/licenses/license-7","http://w3id.org/arkumu/licenses/license-8","http://w3id.org/arkumu/licenses/license-9"],"internationa":["http://w3id.org/arkumu/licenses/license-5","http://w3id.org/arkumu/licenses/license-6","http://w3id.org/arkumu/licenses/license-7","http://w3id.org/arkumu/licenses/license-8","http://w3id.org/arkumu/licenses/license-9"],"internation":["http://w3id.org/arkumu/licenses/license-5","http://w3id.org/arkumu/licenses/license-6","http://w3id.org/arkumu/licenses/license-7","http://w3id.org/arkumu/licenses/license-8","http://w3id.org/arkumu/licenses/license-9"],"internatio":["http://w3id.org/arkumu/licenses/license-5","http://w3id.org/arkumu/licenses/license-6","http://w3id.org/arkumu/licenses/license-7","http://w3id.org/arkumu/licenses/license-8","http://w3id.org/arkumu/licenses/license-9"],"internati":["http://w3id.org/arkumu/licenses/license-5","http://w3id.org/arkumu/licenses/license-6","http://w3id.org/arkumu/licenses/license-7","http://w3id.org/arkumu/licenses/license-8","http://w3id.org/arkumu/licenses/license-9"],"internat":["http://w3id.org/arkumu/licenses/license-5","http://w3id.org/arkumu/licenses/license-6","http://w3id.org/arkumu/licenses/license-7","http://w3id.org/arkumu/licenses/license-8","http://w3id.org/arkumu/licenses/license-9"],"interna":["http://w3id.org/arkumu/licenses/license-5","http://w3id.org/arkumu/licenses/license-6","http://w3id.org/arkumu/licenses/license-7","http://w3id.org/arkumu/licenses/license-8","http://w3id.org/arkumu/licenses/license-9"],"intern":["http://w3id.org/arkumu/licenses/license-5","http://w3id.org/arkumu/licenses/license-6","http://w3id.org/arkumu/licenses/license-7","http://w3id.org/arkumu/licenses/license-8","http://w3id.org/arkumu/licenses/license-9"],"inter":["http://w3id.org/arkumu/licenses/license-5","http://w3id.org/arkumu/licenses/license-6","http://w3id.org/arkumu/licenses/license-7","http://w3id.org/arkumu/licenses/license-8","http://w3id.org/arkumu/licenses/license-9"],"inte":["http://w3id.org/arkumu/licenses/license-5","http://w3id.org/arkumu/licenses/license-6","http://w3id.org/arkumu/licenses/license-7","http://w3id.org/arkumu/licenses/license-8","http://w3id.org/arkumu/licenses/license-9"],"int":["http://w3id.org/arkumu/licenses/license-5","http://w3id.org/arkumu/licenses/license-6","http://w3id.org/arkumu/licenses/license-7","http://w3id.org/arkumu/licenses/license-8","http://w3id.org/arkumu/licenses/license-9"],"in":["http://w3id.org/arkumu/licenses/license-5","http://w3id.org/arkumu/licenses/license-6","http://w3id.org/arkumu/licenses/license-7","http://w3id.org/arkumu/licenses/license-8","http://w3id.org/arkumu/licenses/license-9"],"derivatives":["http://w3id.org/arkumu/licenses/license-6"],"derivative":["http://w3id.org/arkumu/licenses/license-6"],"derivativ":["http://w3id.org/arkumu/licenses/license-6"],"derivati":["http://w3id.org/arkumu/licenses/license-6"],"derivat":["http://w3id.org/arkumu/licenses/license-6"],"deriva":["http://w3id.org/arkumu/licenses/license-6"],"deriv":["http://w3id.org/arkumu/licenses/license-6"],"deri":["http://w3id.org/arkumu/licenses/license-6"],"der":["http://w3id.org/arkumu/licenses/license-6"],"de":["http://w3id.org/arkumu/licenses/license-6"],"erivatives":["http://w3id.org/arkumu/licenses/license-6","http://w3id.org/arkumu/licenses/license-8"],"erivative":["http://w3id.org/arkumu/licenses/license-6","http://w3id.org/arkumu/licenses/license-8"],"erivativ":["http://w3id.org/arkumu/licenses/license-6","http://w3id.org/arkumu/licenses/license-8"],"erivati":["http://w3id.org/arkumu/licenses/license-6","http://w3id.org/arkumu/licenses/license-8"],"erivat":["http://w3id.org/arkumu/licenses/license-6","http://w3id.org/arkumu/licenses/license-8"],"eriva":["http://w3id.org/arkumu/licenses/license-6","http://w3id.org/arkumu/licenses/license-8"],"eriv":["http://w3id.org/arkumu/licenses/license-6","http://w3id.org/arkumu/licenses/license-8"],"eri":["http://w3id.org/arkumu/licenses/license-6","http://w3id.org/arkumu/licenses/license-8"],"rivatives":["http://w3id.org/arkumu/licenses/license-6","http://w3id.org/arkumu/licenses/license-8"],"rivative":["http://w3id.org/arkumu/licenses/license-6","http://w3id.org/arkumu/licenses/license-8"],"rivativ":["http://w3id.org/arkumu/licenses/license-6","http://w3id.org/arkumu/licenses/license-8"],"rivati":["http://w3id.org/arkumu/licenses/license-6","http://w3id.org/arkumu/licenses/license-8"],"rivat":["http://w3id.org/arkumu/licenses/license-6","http://w3id.org/arkumu/licenses/license-8"],"riva":["http://w3id.org/arkumu/licenses/license-6","http://w3id.org/arkumu/licenses/license-8"],"riv":["http://w3id.org/arkumu/licenses/license-6","http://w3id.org/arkumu/licenses/license-8"],"harealike":["http://w3id.org/arkumu/licenses/license-7"],"harealik":["http://w3id.org/arkumu/licenses/license-7"],"hareali":["http://w3id.org/arkumu/licenses/license-7"],"hareal":["http://w3id.org/arkumu/licenses/license-7"],"harea":["http://w3id.org/arkumu/licenses/license-7"],"hare":["http://w3id.org/arkumu/licenses/license-7"],"har":["http://w3id.org/arkumu/licenses/license-7"],"h":["http://w3id.org/arkumu/licenses/license-7"],"arealike":["http://w3id.org/arkumu/licenses/license-7","http://w3id.org/arkumu/licenses/license-9"],"arealik":["http://w3id.org/arkumu/licenses/license-7","http://w3id.org/arkumu/licenses/license-9"],"areali":["http://w3id.org/arkumu/licenses/license-7","http://w3id.org/arkumu/licenses/license-9"],"areal":["http://w3id.org/arkumu/licenses/license-7","http://w3id.org/arkumu/licenses/license-9"],"area":["http://w3id.org/arkumu/licenses/license-7","http://w3id.org/arkumu/licenses/license-9"],"are":["http://w3id.org/arkumu/licenses/license-7","http://w3id.org/arkumu/licenses/license-9"],"ivatives":["http://w3id.org/arkumu/licenses/license-8"],"ivative":["http://w3id.org/arkumu/licenses/license-8"],"ivativ":["http://w3id.org/arkumu/licenses/license-8"],"ivati":["http://w3id.org/arkumu/licenses/license-8"],"ivat":["http://w3id.org/arkumu/licenses/license-8"],"iva":["http://w3id.org/arkumu/licenses/license-8"],"iv":["http://w3id.org/arkumu/licenses/license-8"],"realike":["http://w3id.org/arkumu/licenses/license-9"],"realik":["http://w3id.org/arkumu/licenses/license-9"],"reali":["http://w3id.org/arkumu/licenses/license-9"],"real":["http://w3id.org/arkumu/licenses/license-9"],"rea":["http://w3id.org/arkumu/licenses/license-9"],"re":["http://w3id.org/arkumu/licenses/license-9"]},{"0":["http://w3id.org/arkumu/licenses/license-3"],"c":["http://w3id.org/arkumu/licenses/license-10"],"in":["http://w3id.org/arkumu/licenses/license-10"],"n":["http://w3id.org/arkumu/licenses/license-10"],"rk":["http://w3id.org/arkumu/licenses/license-10"],"r":["http://w3id.org/arkumu/licenses/license-10"],"k":["http://w3id.org/arkumu/licenses/license-10"],"niversal":["http://w3id.org/arkumu/licenses/license-10"],"niversa":["http://w3id.org/arkumu/licenses/license-10"],"nivers":["http://w3id.org/arkumu/licenses/license-10"],"niver":["http://w3id.org/arkumu/licenses/license-10"],"nive":["http://w3id.org/arkumu/licenses/license-10"],"niv":["http://w3id.org/arkumu/licenses/license-10"],"ni":["http://w3id.org/arkumu/licenses/license-10"],"iversal":["http://w3id.org/arkumu/licenses/license-10"],"iversa":["http://w3id.org/arkumu/licenses/license-10"],"ivers":["http://w3id.org/arkumu/licenses/license-10"],"iver":["http://w3id.org/arkumu/licenses/license-10"],"ive":["http://w3id.org/arkumu/licenses/license-10"],"iv":["http://w3id.org/arkumu/licenses/license-10","http://w3id.org/arkumu/licenses/license-6"],"versal":["http://w3id.org/arkumu/licenses/license-10"],"versa":["http://w3id.org/arkumu/licenses/license-10"],"vers":["http://w3id.org/arkumu/licenses/license-10"],"ver":["http://w3id.org/arkumu/licenses/license-10"],"ve":["http://w3id.org/arkumu/licenses/license-10"],"v":["http://w3id.org/arkumu/licenses/license-10","http://w3id.org/arkumu/licenses/license-6","http://w3id.org/arkumu/licenses/license-8"],"ght":["http://w3id.org/arkumu/licenses/license-11"],"gh":["http://w3id.org/arkumu/licenses/license-11"],"g":["http://w3id.org/arkumu/licenses/license-11"],"ht":["http://w3id.org/arkumu/licenses/license-11"],"h":["http://w3id.org/arkumu/licenses/license-11"],"aned":["http://w3id.org/arkumu/licenses/license-11"],"ane":["http://w3id.org/arkumu/licenses/license-11"],"an":["http://w3id.org/arkumu/licenses/license-11"],"a":["http://w3id.org/arkumu/licenses/license-11"],"ned":["http://w3id.org/arkumu/licenses/license-11"],"ne":["http://w3id.org/arkumu/licenses/license-11"],"ork":["http://w3id.org/arkumu/licenses/license-11"],"ution":["http://w3id.org/arkumu/licenses/license-4","http://w3id.org/arkumu/licenses/license-5","http://w3id.org/arkumu/licenses/license-6","http://w3id.org/arkumu/licenses/license-7","http://w3id.org/arkumu/licenses/license-8","http://w3id.org/arkumu/licenses/license-9"],"utio":["http://w3id.org/arkumu/licenses/license-4","http://w3id.org/arkumu/licenses/license-5","http://w3id.org/arkumu/licenses/license-6","http://w3id.org/arkumu/licenses/license-7","http://w3id.org/arkumu/licenses/license-8","http://w3id.org/arkumu/licenses/license-9"],"uti":["http://w3id.org/arkumu/licenses/license-4","http://w3id.org/arkumu/licenses/license-5","http://w3id.org/arkumu/licenses/license-6","http://w3id.org/arkumu/licenses/license-7","http://w3id.org/arkumu/licenses/license-8","http://w3id.org/arkumu/licenses/license-9"],"ut":["http://w3id.org/arkumu/licenses/license-4","http://w3id.org/arkumu/licenses/license-5","http://w3id.org/arkumu/licenses/license-6","http://w3id.org/arkumu/licenses/license-7","http://w3id.org/arkumu/licenses/license-8","http://w3id.org/arkumu/licenses/license-9"],"u":["http://w3id.org/arkumu/licenses/license-4","http://w3id.org/arkumu/licenses/license-5","http://w3id.org/arkumu/licenses/license-6","http://w3id.org/arkumu/licenses/license-7","http://w3id.org/arkumu/licenses/license-8","http://w3id.org/arkumu/licenses/license-9"],"tion":["http://w3id.org/arkumu/licenses/license-4","http://w3id.org/arkumu/licenses/license-5","http://w3id.org/arkumu/licenses/license-6","http://w3id.org/arkumu/licenses/license-7","http://w3id.org/arkumu/licenses/license-8","http://w3id.org/arkumu/licenses/license-9"],"tio":["http://w3id.org/arkumu/licenses/license-4","http://w3id.org/arkumu/licenses/license-5","http://w3id.org/arkumu/licenses/license-6","http://w3id.org/arkumu/licenses/license-7","http://w3id.org/arkumu/licenses/license-8","http://w3id.org/arkumu/licenses/license-9"],"ti":["http://w3id.org/arkumu/licenses/license-4","http://w3id.org/arkumu/licenses/license-5","http://w3id.org/arkumu/licenses/license-6","http://w3id.org/arkumu/licenses/license-7","http://w3id.org/arkumu/licenses/license-8","http://w3id.org/arkumu/licenses/license-9"],"rnational":["http://w3id.org/arkumu/licenses/license-4","http://w3id.org/arkumu/licenses/license-5","http://w3id.org/arkumu/licenses/license-6","http://w3id.org/arkumu/licenses/license-7","http://w3id.org/arkumu/licenses/license-8","http://w3id.org/arkumu/licenses/license-9"],"rnationa":["http://w3id.org/arkumu/licenses/license-4","http://w3id.org/arkumu/licenses/license-5","http://w3id.org/arkumu/licenses/license-6","http://w3id.org/arkumu/licenses/license-7","http://w3id.org/arkumu/licenses/license-8","http://w3id.org/arkumu/licenses/license-9"],"rnation":["http://w3id.org/arkumu/licenses/license-4","http://w3id.org/arkumu/licenses/license-5","http://w3id.org/arkumu/licenses/license-6","http://w3id.org/arkumu/licenses/license-7","http://w3id.org/arkumu/licenses/license-8","http://w3id.org/arkumu/licenses/license-9"],"rnatio":["http://w3id.org/arkumu/licenses/license-4","http://w3id.org/arkumu/licenses/license-5","http://w3id.org/arkumu/licenses/license-6","http://w3id.org/arkumu/licenses/license-7","http://w3id.org/arkumu/licenses/license-8","http://w3id.org/arkumu/licenses/license-9"],"rnati":["http://w3id.org/arkumu/licenses/license-4","http://w3id.org/arkumu/licenses/license-5","http://w3id.org/arkumu/licenses/license-6","http://w3id.org/arkumu/licenses/license-7","http://w3id.org/arkumu/licenses/license-8","http://w3id.org/arkumu/licenses/license-9"],"rnat":["http://w3id.org/arkumu/licenses/license-4","http://w3id.org/arkumu/licenses/license-5","http://w3id.org/arkumu/licenses/license-6","http://w3id.org/arkumu/licenses/license-7","http://w3id.org/arkumu/licenses/license-8","http://w3id.org/arkumu/licenses/license-9"],"rna":["http://w3id.org/arkumu/licenses/license-4","http://w3id.org/arkumu/licenses/license-5","http://w3id.org/arkumu/licenses/license-6","http://w3id.org/arkumu/licenses/license-7","http://w3id.org/arkumu/licenses/license-8","http://w3id.org/arkumu/licenses/license-9"],"rn":["http://w3id.org/arkumu/licenses/license-4","http://w3id.org/arkumu/licenses/license-5","http://w3id.org/arkumu/licenses/license-6","http://w3id.org/arkumu/licenses/license-7","http://w3id.org/arkumu/licenses/license-8","http://w3id.org/arkumu/licenses/license-9"],"national":["http://w3id.org/arkumu/licenses/license-4","http://w3id.org/arkumu/licenses/license-5","http://w3id.org/arkumu/licenses/license-8","http://w3id.org/arkumu/licenses/license-9"],"nationa":["http://w3id.org/arkumu/licenses/license-4","http://w3id.org/arkumu/licenses/license-5","http://w3id.org/arkumu/licenses/license-8","http://w3id.org/arkumu/licenses/license-9"],"nation":["http://w3id.org/arkumu/licenses/license-4","http://w3id.org/arkumu/licenses/license-5","http://w3id.org/arkumu/licenses/license-8","http://w3id.org/arkumu/licenses/license-9"],"natio":["http://w3id.org/arkumu/licenses/license-4","http://w3id.org/arkumu/licenses/license-5","http://w3id.org/arkumu/licenses/license-8","http://w3id.org/arkumu/licenses/license-9"],"nati":["http://w3id.org/arkumu/licenses/license-4","http://w3id.org/arkumu/licenses/license-5","http://w3id.org/arkumu/licenses/license-8","http://w3id.org/arkumu/licenses/license-9"],"nat":["http://w3id.org/arkumu/licenses/license-4","http://w3id.org/arkumu/licenses/license-5","http://w3id.org/arkumu/licenses/license-8","http://w3id.org/arkumu/licenses/license-9"],"na":["http://w3id.org/arkumu/licenses/license-4","http://w3id.org/arkumu/licenses/license-5","http://w3id.org/arkumu/licenses/license-8","http://w3id.org/arkumu/licenses/license-9"],"ational":["http://w3id.org/arkumu/licenses/license-4"],"ationa":["http://w3id.org/arkumu/licenses/license-4"],"ation":["http://w3id.org/arkumu/licenses/license-4"],"atio":["http://w3id.org/arkumu/licenses/license-4"],"ati":["http://w3id.org/arkumu/licenses/license-4","http://w3id.org/arkumu/licenses/license-6","http://w3id.org/arkumu/licenses/license-8"],"ion":["http://w3id.org/arkumu/licenses/license-5","http://w3id.org/arkumu/licenses/license-6","http://w3id.org/arkumu/licenses/license-7","http://w3id.org/arkumu/licenses/license-8","http://w3id.org/arkumu/licenses/license-9"],"io":["http://w3id.org/arkumu/licenses/license-5","http://w3id.org/arkumu/licenses/license-6","http://w3id.org/arkumu/licenses/license-7","http://w3id.org/arkumu/licenses/license-8","http://w3id.org/arkumu/licenses/license-9"],"mercial":["http://w3id.org/arkumu/licenses/license-5","http://w3id.org/arkumu/licenses/license-6","http://w3id.org/arkumu/licenses/license-7"],"mercia":["http://w3id.org/arkumu/licenses/license-5","http://w3id.org/arkumu/licenses/license-6","http://w3id.org/arkumu/licenses/license-7"],"merci":["http://w3id.org/arkumu/licenses/license-5","http://w3id.org/arkumu/licenses/license-6","http://w3id.org/arkumu/licenses/license-7"],"merc":["http://w3id.org/arkumu/licenses/license-5","http://w3id.org/arkumu/licenses/license-6","http://w3id.org/arkumu/licenses/license-7"],"mer":["http://w3id.org/arkumu/licenses/license-5","http://w3id.org/arkumu/licenses/license-6","http://w3id.org/arkumu/licenses/license-7"],"me":["http://w3id.org/arkumu/licenses/license-5","http://w3id.org/arkumu/licenses/license-6","http://w3id.org/arkumu/licenses/license-7"],"ercial":["http://w3id.org/arkumu/licenses/license-5","http://w3id.org/arkumu/licenses/license-6","http://w3id.org/arkumu/licenses/license-7"],"ercia":["http://w3id.org/arkumu/licenses/license-5","http://w3id.org/arkumu/licenses/license-6","http://w3id.org/arkumu/licenses/license-7"],"erci":["http://w3id.org/arkumu/licenses/license-5","http://w3id.org/arkumu/licenses/license-6","http://w3id.org/arkumu/licenses/license-7"],"erc":["http://w3id.org/arkumu/licenses/license-5","http://w3id.org/arkumu/licenses/license-6","http://w3id.org/arkumu/licenses/license-7"],"er":["http://w3id.org/arkumu/licenses/license-5","http://w3id.org/arkumu/licenses/license-6","http://w3id.org/arkumu/licenses/license-7","http://w3id.org/arkumu/licenses/license-9"],"e":["http://w3id.org/arkumu/licenses/license-5","http://w3id.org/arkumu/licenses/license-6","http://w3id.org/arkumu/licenses/license-7","http://w3id.org/arkumu/licenses/license-9"],"rcial":["http://w3id.org/arkumu/licenses/license-5","http://w3id.org/arkumu/licenses/license-6","http://w3id.org/arkumu/licenses/license-7"],"rcia":["http://w3id.org/arkumu/licenses/license-5","http://w3id.org/arkumu/licenses/license-6","http://w3id.org/arkumu/licenses/license-7"],"rci":["http://w3id.org/arkumu/licenses/license-5","http://w3id.org/arkumu/licenses/license-6","http://w3id.org/arkumu/licenses/license-7"],"rc":["http://w3id.org/arkumu/licenses/license-5","http://w3id.org/arkumu/licenses/license-6","http://w3id.org/arkumu/licenses/license-7"],"ernational":["http://w3id.org/arkumu/licenses/license-5","http://w3id.org/arkumu/licenses/license-6","http://w3id.org/arkumu/licenses/license-7","http://w3id.org/arkumu/licenses/license-8","http://w3id.org/arkumu/licenses/license-9"],"ernationa":["http://w3id.org/arkumu/licenses/license-5","http://w3id.org/arkumu/licenses/license-6","http://w3id.org/arkumu/licenses/license-7","http://w3id.org/arkumu/licenses/license-8","http://w3id.org/arkumu/licenses/license-9"],"ernation":["http://w3id.org/arkumu/licenses/license-5","http://w3id.org/arkumu/licenses/license-6","http://w3id.org/arkumu/licenses/license-7","http://w3id.org/arkumu/licenses/license-8","http://w3id.org/arkumu/licenses/license-9"],"ernatio":["http://w3id.org/arkumu/licenses/license-5","http://w3id.org/arkumu/licenses/license-6","http://w3id.org/arkumu/licenses/license-7","http://w3id.org/arkumu/licenses/license-8","http://w3id.org/arkumu/licenses/license-9"],"ernati":["http://w3id.org/arkumu/licenses/license-5","http://w3id.org/arkumu/licenses/license-6","http://w3id.org/arkumu/licenses/license-7","http://w3id.org/arkumu/licenses/license-8","http://w3id.org/arkumu/licenses/license-9"],"ernat":["http://w3id.org/arkumu/licenses/license-5","http://w3id.org/arkumu/licenses/license-6","http://w3id.org/arkumu/licenses/license-7","http://w3id.org/arkumu/licenses/license-8","http://w3id.org/arkumu/licenses/license-9"],"erna":["http://w3id.org/arkumu/licenses/license-5","http://w3id.org/arkumu/licenses/license-6","http://w3id.org/arkumu/licenses/license-7","http://w3id.org/arkumu/licenses/license-8","http://w3id.org/arkumu/licenses/license-9"],"ern":["http://w3id.org/arkumu/licenses/license-5","http://w3id.org/arkumu/licenses/license-6","http://w3id.org/arkumu/licenses/license-7","http://w3id.org/arkumu/licenses/license-8","http://w3id.org/arkumu/licenses/license-9"],"ivatives":["http://w3id.org/arkumu/licenses/license-6"],"ivative":["http://w3id.org/arkumu/licenses/license-6"],"ivativ":["http://w3id.org/arkumu/licenses/license-6"],"ivati":["http://w3id.org/arkumu/licenses/license-6"],"ivat":["http://w3id.org/arkumu/licenses/license-6"],"iva":["http://w3id.org/arkumu/licenses/license-6"],"vatives":["http://w3id.org/arkumu/licenses/license-6","http://w3id.org/arkumu/licenses/license-8"],"vative":["http://w3id.org/arkumu/licenses/license-6","http://w3id.org/arkumu/licenses/license-8"],"vativ":["http://w3id.org/arkumu/licenses/license-6","http://w3id.org/arkumu/licenses/license-8"],"vati":["http://w3id.org/arkumu/licenses/license-6","http://w3id.org/arkumu/licenses/license-8"],"vat":["http://w3id.org/arkumu/licenses/license-6","http://w3id.org/arkumu/licenses/license-8"],"va":["http://w3id.org/arkumu/licenses/license-6","http://w3id.org/arkumu/licenses/license-8"],"atives":["http://w3id.org/arkumu/licenses/license-6","http://w3id.org/arkumu/licenses/license-8"],"ative":["http://w3id.org/arkumu/licenses/license-6","http://w3id.org/arkumu/licenses/license-8"],"ativ":["http://w3id.org/arkumu/licenses/license-6","http://w3id.org/arkumu/licenses/license-8"],"ternational":["http://w3id.org/arkumu/licenses/license-6","http://w3id.org/arkumu/licenses/license-7"],"ternationa":["http://w3id.org/arkumu/licenses/license-6","http://w3id.org/arkumu/licenses/license-7"],"ternation":["http://w3id.org/arkumu/licenses/license-6","http://w3id.org/arkumu/licenses/license-7"],"ternatio":["http://w3id.org/arkumu/licenses/license-6","http://w3id.org/arkumu/licenses/license-7"],"ternati":["http://w3id.org/arkumu/licenses/license-6","http://w3id.org/arkumu/licenses/license-7"],"ternat":["http://w3id.org/arkumu/licenses/license-6","http://w3id.org/arkumu/licenses/license-7"],"terna":["http://w3id.org/arkumu/licenses/license-6","http://w3id.org/arkumu/licenses/license-7"],"tern":["http://w3id.org/arkumu/licenses/license-6","http://w3id.org/arkumu/licenses/license-7"],"ter":["http://w3id.org/arkumu/licenses/license-6","http://w3id.org/arkumu/licenses/license-7"],"te":["http://w3id.org/arkumu/licenses/license-6","http://w3id.org/arkumu/licenses/license-7"],"realike":["http://w3id.org/arkumu/licenses/license-7"],"realik":["http://w3id.org/arkumu/licenses/license-7"],"reali":["http://w3id.org/arkumu/licenses/license-7"],"real":["http://w3id.org/arkumu/licenses/license-7"],"rea":["http://w3id.org/arkumu/licenses/license-7"],"re":["http://w3id.org/arkumu/licenses/license-7"],"ealike":["http://w3id.org/arkumu/licenses/license-7","http://w3id.org/arkumu/licenses/license-9"],"ealik":["http://w3id.org/arkumu/licenses/license-7","http://w3id.org/arkumu/licenses/license-9"],"eali":["http://w3id.org/arkumu/licenses/license-7","http://w3id.org/arkumu/licenses/license-9"],"eal":["http://w3id.org/arkumu/licenses/license-7","http://w3id.org/arkumu/licenses/license-9"],"ea":["http://w3id.org/arkumu/licenses/license-7","http://w3id.org/arkumu/licenses/license-9"],"alike":["http://w3id.org/arkumu/licenses/license-7","http://w3id.org/arkumu/licenses/license-9"],"alik":["http://w3id.org/arkumu/licenses/license-7","http://w3id.org/arkumu/licenses/license-9"],"ali":["http://w3id.org/arkumu/licenses/license-7","http://w3id.org/arkumu/licenses/license-9"],"tives":["http://w3id.org/arkumu/licenses/license-8"],"tive":["http://w3id.org/arkumu/licenses/license-8"],"tiv":["http://w3id.org/arkumu/licenses/license-8"],"al":["http://w3id.org/arkumu/licenses/license-9"],"like":["http://w3id.org/arkumu/licenses/license-9"],"lik":["http://w3id.org/arkumu/licenses/license-9"],"li":["http://w3id.org/arkumu/licenses/license-9"],"l":["http://w3id.org/arkumu/licenses/license-9"]},{"ersal":["http://w3id.org/arkumu/licenses/license-10"],"ersa":["http://w3id.org/arkumu/licenses/license-10"],"ers":["http://w3id.org/arkumu/licenses/license-10"],"er":["http://w3id.org/arkumu/licenses/license-10"],"e":["http://w3id.org/arkumu/licenses/license-10"],"rsal":["http://w3id.org/arkumu/licenses/license-10"],"rsa":["http://w3id.org/arkumu/licenses/license-10"],"rs":["http://w3id.org/arkumu/licenses/license-10"],"t":["http://w3id.org/arkumu/licenses/license-11"],"ed":["http://w3id.org/arkumu/licenses/license-11"],"rk":["http://w3id.org/arkumu/licenses/license-11"],"ion":["http://w3id.org/arkumu/licenses/license-4"],"io":["http://w3id.org/arkumu/licenses/license-4"],"on":["http://w3id.org/arkumu/licenses/license-4","http://w3id.org/arkumu/licenses/license-5","http://w3id.org/arkumu/licenses/license-6","http://w3id.org/arkumu/licenses/license-7","http://w3id.org/arkumu/licenses/license-8","http://w3id.org/arkumu/licenses/license-9"],"o":["http://w3id.org/arkumu/licenses/license-4","http://w3id.org/arkumu/licenses/license-5","http://w3id.org/arkumu/licenses/license-6","http://w3id.org/arkumu/licenses/license-7","http://w3id.org/arkumu/licenses/license-8","http://w3id.org/arkumu/licenses/license-9"],"n":["http://w3id.org/arkumu/licenses/license-4","http://w3id.org/arkumu/licenses/license-9"],"tional":["http://w3id.org/arkumu/licenses/license-4","http://w3id.org/arkumu/licenses/license-5","http://w3id.org/arkumu/licenses/license-6","http://w3id.org/arkumu/licenses/license-7","http://w3id.org/arkumu/licenses/license-8","http://w3id.org/arkumu/licenses/license-9"],"tiona":["http://w3id.org/arkumu/licenses/license-4","http://w3id.org/arkumu/licenses/license-5","http://w3id.org/arkumu/licenses/license-6","http://w3id.org/arkumu/licenses/license-7","http://w3id.org/arkumu/licenses/license-8","http://w3id.org/arkumu/licenses/license-9"],"ional":["http://w3id.org/arkumu/licenses/license-4","http://w3id.org/arkumu/licenses/license-5","http://w3id.org/arkumu/licenses/license-8","http://w3id.org/arkumu/licenses/license-9"],"iona":["http://w3id.org/arkumu/licenses/license-4","http://w3id.org/arkumu/licenses/license-5","http://w3id.org/arkumu/licenses/license-8","http://w3id.org/arkumu/licenses/license-9"],"cial":["http://w3id.org/arkumu/licenses/license-5","http://w3id.org/arkumu/licenses/license-6","http://w3id.org/arkumu/licenses/license-7"],"cia":["http://w3id.org/arkumu/licenses/license-5","http://w3id.org/arkumu/licenses/license-6","http://w3id.org/arkumu/licenses/license-7"],"ci":["http://w3id.org/arkumu/licenses/license-5","http://w3id.org/arkumu/licenses/license-6","http://w3id.org/arkumu/licenses/license-7"],"ial":["http://w3id.org/arkumu/licenses/license-5","http://w3id.org/arkumu/licenses/license-6","http://w3id.org/arkumu/licenses/license-7"],"ia":["http://w3id.org/arkumu/licenses/license-5","http://w3id.org/arkumu/licenses/license-6","http://w3id.org/arkumu/licenses/license-7"],"al":["http://w3id.org/arkumu/licenses/license-5","http://w3id.org/arkumu/licenses/license-6","http://w3id.org/arkumu/licenses/license-7"],"ational":["http://w3id.org/arkumu/licenses/license-5","http://w3id.org/arkumu/licenses/license-6","http://w3id.org/arkumu/licenses/license-7","http://w3id.org/arkumu/licenses/license-8","http://w3id.org/arkumu/licenses/license-9"],"ationa":["http://w3id.org/arkumu/licenses/license-5","http://w3id.org/arkumu/licenses/license-6","http://w3id.org/arkumu/licenses/license-7","http://w3id.org/arkumu/licenses/license-8","http://w3id.org/arkumu/licenses/license-9"],"ation":["http://w3id.org/arkumu/licenses/license-5","http://w3id.org/arkumu/licenses/license-6","http://w3id.org/arkumu/licenses/license-7","http://w3id.org/arkumu/licenses/license-8","http://w3id.org/arkumu/licenses/license-9"],"atio":["http://w3id.org/arkumu/licenses/license-5","http://w3id.org/arkumu/licenses/license-6","http://w3id.org/arkumu/licenses/license-7","http://w3id.org/arkumu/licenses/license-8","http://w3id.org/arkumu/licenses/license-9"],"ati":["http://w3id.org/arkumu/licenses/license-5","http://w3id.org/arkumu/licenses/license-7","http://w3id.org/arkumu/licenses/license-9"],"tives":["http://w3id.org/arkumu/licenses/license-6"],"tive":["http://w3id.org/arkumu/licenses/license-6"],"tiv":["http://w3id.org/arkumu/licenses/license-6"],"ives":["http://w3id.org/arkumu/licenses/license-6","http://w3id.org/arkumu/licenses/license-8"],"ive":["http://w3id.org/arkumu/licenses/license-6","http://w3id.org/arkumu/licenses/license-8"],"ves":["http://w3id.org/arkumu/licenses/license-6","http://w3id.org/arkumu/licenses/license-8"],"ve":["http://w3id.org/arkumu/licenses/license-6","http://w3id.org/arkumu/licenses/license-8"],"national":["http://w3id.org/arkumu/licenses/license-6","http://w3id.org/arkumu/licenses/license-7"],"nationa":["http://w3id.org/arkumu/licenses/license-6","http://w3id.org/arkumu/licenses/license-7"],"nation":["http://w3id.org/arkumu/licenses/license-6","http://w3id.org/arkumu/licenses/license-7"],"natio":["http://w3id.org/arkumu/licenses/license-6","http://w3id.org/arkumu/licenses/license-7"],"nati":["http://w3id.org/arkumu/licenses/license-6","http://w3id.org/arkumu/licenses/license-7"],"nat":["http://w3id.org/arkumu/licenses/license-6","http://w3id.org/arkumu/licenses/license-7"],"na":["http://w3id.org/arkumu/licenses/license-6","http://w3id.org/arkumu/licenses/license-7"],"like":["http://w3id.org/arkumu/licenses/license-7"],"lik":["http://w3id.org/arkumu/licenses/license-7"],"li":["http://w3id.org/arkumu/licenses/license-7"],"ike":["http://w3id.org/arkumu/licenses/license-7","http://w3id.org/arkumu/licenses/license-9"],"ik":["http://w3id.org/arkumu/licenses/license-7","http://w3id.org/arkumu/licenses/license-9"],"ke":["http://w3id.org/arkumu/licenses/license-7","http://w3id.org/arkumu/licenses/license-9"],"k":["http://w3id.org/arkumu/licenses/license-7","http://w3id.org/arkumu/licenses/license-9"],"es":["http://w3id.org/arkumu/licenses/license-8"]},{"sal":["http://w3id.org/arkumu/licenses/license-10"],"sa":["http://w3id.org/arkumu/licenses/license-10"],"s":["http://w3id.org/arkumu/licenses/license-10","http://w3id.org/arkumu/licenses/license-6","http://w3id.org/arkumu/licenses/license-8"],"al":["http://w3id.org/arkumu/licenses/license-10","http://w3id.org/arkumu/licenses/license-4","http://w3id.org/arkumu/licenses/license-8"],"d":["http://w3id.org/arkumu/licenses/license-11"],"k":["http://w3id.org/arkumu/licenses/license-11"],"onal":["http://w3id.org/arkumu/licenses/license-4","http://w3id.org/arkumu/licenses/license-5","http://w3id.org/arkumu/licenses/license-6","http://w3id.org/arkumu/licenses/license-7","http://w3id.org/arkumu/licenses/license-8","http://w3id.org/arkumu/licenses/license-9"],"ona":["http://w3id.org/arkumu/licenses/license-4","http://w3id.org/arkumu/licenses/license-5","http://w3id.org/arkumu/licenses/license-6","http://w3id.org/arkumu/licenses/license-7","http://w3id.org/arkumu/licenses/license-8","http://w3id.org/arkumu/licenses/license-9"],"nal":["http://w3id.org/arkumu/licenses/license-4","http://w3id.org/arkumu/licenses/license-5","http://w3id.org/arkumu/licenses/license-6","http://w3id.org/arkumu/licenses/license-7","http://w3id.org/arkumu/licenses/license-8","http://w3id.org/arkumu/licenses/license-9"],"l":["http://w3id.org/arkumu/licenses/license-5","http://w3id.org/arkumu/licenses/license-6","http://w3id.org/arkumu/licenses/license-7"],"es":["http://w3id.org/arkumu/licenses/license-6"],"ional":["http://w3id.org/arkumu/licenses/license-6","http://w3id.org/arkumu/licenses/license-7"],"iona":["http://w3id.org/arkumu/licenses/license-6","http://w3id.org/arkumu/licenses/license-7"]},{"l":["http://w3id.org/arkumu/licenses/license-4","http://w3id.org/arkumu/licenses/license-8"]}]